[{"Cookie":"ASP.NET_SessionId=e3c0zo2ghof1drn1lyhzsoqm; path=/; HttpOnly","CaptchaKey":"24066","CaptchaPath":"http://procesos.ramajudicial.gov.co/consultaprocesos/Captcha/CaptchaHandler.ashx?key=24066","ProcessNumber":null,"CaptchaResult":0,"ResultData":null},{"Cookie":"ASP.NET_SessionId=xitkiuuclmlllytbloqn0ra0; path=/; HttpOnly","CaptchaKey":"9310","CaptchaPath":"http://procesos.ramajudicial.gov.co/consultaprocesos/Captcha/CaptchaHandler.ashx?key=9310","ProcessNumber":null,"CaptchaResult":0,"ResultData":null},{"Cookie":"ASP.NET_SessionId=pb4g1ovmihejxawxlnnaguth; path=/; HttpOnly","CaptchaKey":"94553","CaptchaPath":"http://procesos.ramajudicial.gov.co/consultaprocesos/Captcha/CaptchaHandler.ashx?key=94553","ProcessNumber":null,"CaptchaResult":0,"ResultData":null},{"Cookie":"ASP.NET_SessionId=nt3vtcewion3y5m4ozqkc5xx; path=/; HttpOnly","CaptchaKey":"61416","CaptchaPath":"http://procesos.ramajudicial.gov.co/consultaprocesos/Captcha/CaptchaHandler.ashx?key=61416","ProcessNumber":null,"CaptchaResult":0,"ResultData":null},{"Cookie":"ASP.NET_SessionId=dx0ulhscndbfq2xokh4dk1wt; path=/; HttpOnly","CaptchaKey":"84009","CaptchaPath":"http://procesos.ramajudicial.gov.co/consultaprocesos/Captcha/CaptchaHandler.ashx?key=84009","ProcessNumber":null,"CaptchaResult":0,"ResultData":null},{"Cookie":"ASP.NET_SessionId=25u3bsrskqjrrwookpycsx4u; path=/; HttpOnly","CaptchaKey":"69253","CaptchaPath":"http://procesos.ramajudicial.gov.co/consultaprocesos/Captcha/CaptchaHandler.ashx?key=69253","ProcessNumber":null,"CaptchaResult":0,"ResultData":null},{"Cookie":"ASP.NET_SessionId=fgnwcorn0xmq2z00sx51pmru; path=/; HttpOnly","CaptchaKey":"31903","CaptchaPath":"http://procesos.ramajudicial.gov.co/consultaprocesos/Captcha/CaptchaHandler.ashx?key=31903","ProcessNumber":null,"CaptchaResult":0,"ResultData":null},{"Cookie":"ASP.NET_SessionId=rz5yr4ryyw44vpen3f4e5jzd; path=/; HttpOnly","CaptchaKey":"39740","CaptchaPath":"http://procesos.ramajudicial.gov.co/consultaprocesos/Captcha/CaptchaHandler.ashx?key=39740","ProcessNumber":null,"CaptchaResult":0,"ResultData":null},{"Cookie":"ASP.NET_SessionId=eykr0q0xseo2nkxp1c1ivxyz; path=/; HttpOnly","CaptchaKey":"54496","CaptchaPath":"http://procesos.ramajudicial.gov.co/consultaprocesos/Captcha/CaptchaHandler.ashx?key=54496","ProcessNumber":null,"CaptchaResult":0,"ResultData":null},{"Cookie":"ASP.NET_SessionId=1r5drlgmfqcalw4bdtajf1g0; path=/; HttpOnly","CaptchaKey":"14440","CaptchaPath":"http://procesos.ramajudicial.gov.co/consultaprocesos/Captcha/CaptchaHandler.ashx?key=14440","ProcessNumber":null,"CaptchaResult":0,"ResultData":null},{"Cookie":"ASP.NET_SessionId=rvkxtdonbu51nisn0znyukqz; path=/; HttpOnly","CaptchaKey":"51790","CaptchaPath":"http://procesos.ramajudicial.gov.co/consultaprocesos/Captcha/CaptchaHandler.ashx?key=51790","ProcessNumber":null,"CaptchaResult":0,"ResultData":null},{"Cookie":"ASP.NET_SessionId=fkoyilimlphiqbdvhcmfejyw; path=/; HttpOnly","CaptchaKey":"92434","CaptchaPath":"http://procesos.ramajudicial.gov.co/consultaprocesos/Captcha/CaptchaHandler.ashx?key=92434","ProcessNumber":null,"CaptchaResult":0,"ResultData":null},{"Cookie":"ASP.NET_SessionId=yiav5mgmdkhqibpy1hda4l31; path=/; HttpOnly","CaptchaKey":"73465","CaptchaPath":"http://procesos.ramajudicial.gov.co/consultaprocesos/Captcha/CaptchaHandler.ashx?key=73465","ProcessNumber":null,"CaptchaResult":0,"ResultData":null},{"Cookie":"ASP.NET_SessionId=lz2q2vscdmqmmkf3zojs3gue; path=/; HttpOnly","CaptchaKey":"85515","CaptchaPath":"http://procesos.ramajudicial.gov.co/consultaprocesos/Captcha/CaptchaHandler.ashx?key=85515","ProcessNumber":null,"CaptchaResult":0,"ResultData":null},{"Cookie":"ASP.NET_SessionId=g1qynpxiwaadp4en01qes1an; path=/; HttpOnly","CaptchaKey":"74971","CaptchaPath":"http://procesos.ramajudicial.gov.co/consultaprocesos/Captcha/CaptchaHandler.ashx?key=74971","ProcessNumber":null,"CaptchaResult":0,"ResultData":null},{"Cookie":"ASP.NET_SessionId=bdq1azlherlowdeuzaxtryjp; path=/; HttpOnly","CaptchaKey":"75889","CaptchaPath":"http://procesos.ramajudicial.gov.co/consultaprocesos/Captcha/CaptchaHandler.ashx?key=75889","ProcessNumber":null,"CaptchaResult":0,"ResultData":null},{"Cookie":"ASP.NET_SessionId=iewiwo1ebdv2eubocqdlexgc; path=/; HttpOnly","CaptchaKey":"61721","CaptchaPath":"http://procesos.ramajudicial.gov.co/consultaprocesos/Captcha/CaptchaHandler.ashx?key=61721","ProcessNumber":null,"CaptchaResult":0,"ResultData":null},{"Cookie":"ASP.NET_SessionId=llcs0mumtsvugwecokkhcvzp; path=/; HttpOnly","CaptchaKey":"89727","CaptchaPath":"http://procesos.ramajudicial.gov.co/consultaprocesos/Captcha/CaptchaHandler.ashx?key=89727","ProcessNumber":null,"CaptchaResult":0,"ResultData":null},{"Cookie":"ASP.NET_SessionId=injdih1vg5jzobqojcqjlle0; path=/; HttpOnly","CaptchaKey":"77090","CaptchaPath":"http://procesos.ramajudicial.gov.co/consultaprocesos/Captcha/CaptchaHandler.ashx?key=77090","ProcessNumber":null,"CaptchaResult":0,"ResultData":null},{"Cookie":"ASP.NET_SessionId=qs1upkssd5xvhzckmrtbpzyb; path=/; HttpOnly","CaptchaKey":"70758","CaptchaPath":"http://procesos.ramajudicial.gov.co/consultaprocesos/Captcha/CaptchaHandler.ashx?key=70758","ProcessNumber":null,"CaptchaResult":0,"ResultData":null},{"Cookie":"ASP.NET_SessionId=rhr2jfkdxac3kbuzmwffegkq; path=/; HttpOnly","CaptchaKey":"88526","CaptchaPath":"http://procesos.ramajudicial.gov.co/consultaprocesos/Captcha/CaptchaHandler.ashx?key=88526","ProcessNumber":null,"CaptchaResult":0,"ResultData":null},{"Cookie":"ASP.NET_SessionId=eizie3dabuj4vzuyyd1daabh; path=/; HttpOnly","CaptchaKey":"46964","CaptchaPath":"http://procesos.ramajudicial.gov.co/consultaprocesos/Captcha/CaptchaHandler.ashx?key=46964","ProcessNumber":null,"CaptchaResult":0,"ResultData":null},{"Cookie":"ASP.NET_SessionId=j1scztci1qsv1uyjnl1naz4u; path=/; HttpOnly","CaptchaKey":"76477","CaptchaPath":"http://procesos.ramajudicial.gov.co/consultaprocesos/Captcha/CaptchaHandler.ashx?key=76477","ProcessNumber":null,"CaptchaResult":0,"ResultData":null},{"Cookie":"ASP.NET_SessionId=kncuiw503ggalh5ipzgkaz1q; path=/; HttpOnly","CaptchaKey":"90645","CaptchaPath":"http://procesos.ramajudicial.gov.co/consultaprocesos/Captcha/CaptchaHandler.ashx?key=90645","ProcessNumber":null,"CaptchaResult":0,"ResultData":null},{"Cookie":"ASP.NET_SessionId=hk5w4e030draubvkiwsqitbj; path=/; HttpOnly","CaptchaKey":"17452","CaptchaPath":"http://procesos.ramajudicial.gov.co/consultaprocesos/Captcha/CaptchaHandler.ashx?key=17452","ProcessNumber":null,"CaptchaResult":0,"ResultData":null},{"Cookie":"ASP.NET_SessionId=crkahgss1to0c1ingicg3k4j; path=/; HttpOnly","CaptchaKey":"2083","CaptchaPath":"http://procesos.ramajudicial.gov.co/consultaprocesos/Captcha/CaptchaHandler.ashx?key=2083","ProcessNumber":null,"CaptchaResult":0,"ResultData":null},{"Cookie":"ASP.NET_SessionId=sa2rj4yrbhg24tgqmogsqd2j; path=/; HttpOnly","CaptchaKey":"32208","CaptchaPath":"http://procesos.ramajudicial.gov.co/consultaprocesos/Captcha/CaptchaHandler.ashx?key=32208","ProcessNumber":null,"CaptchaResult":0,"ResultData":null},{"Cookie":"ASP.NET_SessionId=fgofrhxddrpd23aebcptsxgk; path=/; HttpOnly","CaptchaKey":"27078","CaptchaPath":"http://procesos.ramajudicial.gov.co/consultaprocesos/Captcha/CaptchaHandler.ashx?key=27078","ProcessNumber":null,"CaptchaResult":0,"ResultData":null},{"Cookie":"ASP.NET_SessionId=rpbelrnbws2xsnrksfvxnzu5; path=/; HttpOnly","CaptchaKey":"5707","CaptchaPath":"http://procesos.ramajudicial.gov.co/consultaprocesos/Captcha/CaptchaHandler.ashx?key=5707","ProcessNumber":null,"CaptchaResult":0,"ResultData":null},{"Cookie":"ASP.NET_SessionId=f00lvyvwrhpuisx2uz54ynsz; path=/; HttpOnly","CaptchaKey":"1495","CaptchaPath":"http://procesos.ramajudicial.gov.co/consultaprocesos/Captcha/CaptchaHandler.ashx?key=1495","ProcessNumber":null,"CaptchaResult":0,"ResultData":null},{"Cookie":"ASP.NET_SessionId=gxfnxcg1qucgvtgjj0md33iq; path=/; HttpOnly","CaptchaKey":"36421","CaptchaPath":"http://procesos.ramajudicial.gov.co/consultaprocesos/Captcha/CaptchaHandler.ashx?key=36421","ProcessNumber":null,"CaptchaResult":0,"ResultData":null},{"Cookie":"ASP.NET_SessionId=arhb05wgw1vdo0yk0keehtri; path=/; HttpOnly","CaptchaKey":"7213","CaptchaPath":"http://procesos.ramajudicial.gov.co/consultaprocesos/Captcha/CaptchaHandler.ashx?key=7213","ProcessNumber":null,"CaptchaResult":0,"ResultData":null},{"Cookie":"ASP.NET_SessionId=0svsnb4kdye1y3ux4mjqlkw3; path=/; HttpOnly","CaptchaKey":"86737","CaptchaPath":"http://procesos.ramajudicial.gov.co/consultaprocesos/Captcha/CaptchaHandler.ashx?key=86737","ProcessNumber":null,"CaptchaResult":0,"ResultData":null},{"Cookie":"ASP.NET_SessionId=5ok44b4eo1mkyjrbto5rgwm2; path=/; HttpOnly","CaptchaKey":"56307","CaptchaPath":"http://procesos.ramajudicial.gov.co/consultaprocesos/Captcha/CaptchaHandler.ashx?key=56307","ProcessNumber":null,"CaptchaResult":0,"ResultData":null},{"Cookie":"ASP.NET_SessionId=h4sne3pv4xww4h34ht11ninc; path=/; HttpOnly","CaptchaKey":"90950","CaptchaPath":"http://procesos.ramajudicial.gov.co/consultaprocesos/Captcha/CaptchaHandler.ashx?key=90950","ProcessNumber":null,"CaptchaResult":0,"ResultData":null},{"Cookie":"ASP.NET_SessionId=3yusrmrtoa11tobupfcopcob; path=/; HttpOnly","CaptchaKey":"38231","CaptchaPath":"http://procesos.ramajudicial.gov.co/consultaprocesos/Captcha/CaptchaHandler.ashx?key=38231","ProcessNumber":null,"CaptchaResult":0,"ResultData":null},{"Cookie":"ASP.NET_SessionId=ugsylorubfvj2upfopoqc5aq; path=/; HttpOnly","CaptchaKey":"68662","CaptchaPath":"http://procesos.ramajudicial.gov.co/consultaprocesos/Captcha/CaptchaHandler.ashx?key=68662","ProcessNumber":null,"CaptchaResult":0,"ResultData":null},{"Cookie":"ASP.NET_SessionId=cf5ihyc2ycqu42hyxjfuonfh; path=/; HttpOnly","CaptchaKey":"56002","CaptchaPath":"http://procesos.ramajudicial.gov.co/consultaprocesos/Captcha/CaptchaHandler.ashx?key=56002","ProcessNumber":null,"CaptchaResult":0,"ResultData":null},{"Cookie":"ASP.NET_SessionId=3flmojy3ikgr4rm0stx44cty; path=/; HttpOnly","CaptchaKey":"40350","CaptchaPath":"http://procesos.ramajudicial.gov.co/consultaprocesos/Captcha/CaptchaHandler.ashx?key=40350","ProcessNumber":null,"CaptchaResult":0,"ResultData":null},{"Cookie":"ASP.NET_SessionId=emm1i1reytxg3xokvzg0wi0k; path=/; HttpOnly","CaptchaKey":"65955","CaptchaPath":"http://procesos.ramajudicial.gov.co/consultaprocesos/Captcha/CaptchaHandler.ashx?key=65955","ProcessNumber":null,"CaptchaResult":0,"ResultData":null},{"Cookie":"ASP.NET_SessionId=f4no2dekvmggw2nxffi3cxaz; path=/; HttpOnly","CaptchaKey":"36726","CaptchaPath":"http://procesos.ramajudicial.gov.co/consultaprocesos/Captcha/CaptchaHandler.ashx?key=36726","ProcessNumber":null,"CaptchaResult":0,"ResultData":null},{"Cookie":"ASP.NET_SessionId=kagsosyate4d2kuxr4jkip1d; path=/; HttpOnly","CaptchaKey":"35525","CaptchaPath":"http://procesos.ramajudicial.gov.co/consultaprocesos/Captcha/CaptchaHandler.ashx?key=35525","ProcessNumber":null,"CaptchaResult":0,"ResultData":null},{"Cookie":"ASP.NET_SessionId=hh0nydmmjh1i5ri3ip102egm; path=/; HttpOnly","CaptchaKey":"37643","CaptchaPath":"http://procesos.ramajudicial.gov.co/consultaprocesos/Captcha/CaptchaHandler.ashx?key=37643","ProcessNumber":null,"CaptchaResult":0,"ResultData":null},{"Cookie":"ASP.NET_SessionId=onfxlmetprhdpbhc0ahzbgq4; path=/; HttpOnly","CaptchaKey":"41834","CaptchaPath":"http://procesos.ramajudicial.gov.co/consultaprocesos/Captcha/CaptchaHandler.ashx?key=41834","ProcessNumber":null,"CaptchaResult":0,"ResultData":null},{"Cookie":"ASP.NET_SessionId=5jzkx44oc3sqmwtlcx1uxcoy; path=/; HttpOnly","CaptchaKey":"61437","CaptchaPath":"http://procesos.ramajudicial.gov.co/consultaprocesos/Captcha/CaptchaHandler.ashx?key=61437","ProcessNumber":null,"CaptchaResult":0,"ResultData":null},{"Cookie":"ASP.NET_SessionId=lvhx1owjygnuiasjcg2hafgg; path=/; HttpOnly","CaptchaKey":"92456","CaptchaPath":"http://procesos.ramajudicial.gov.co/consultaprocesos/Captcha/CaptchaHandler.ashx?key=92456","ProcessNumber":null,"CaptchaResult":0,"ResultData":null},{"Cookie":"ASP.NET_SessionId=e2bf3r1yi30mq1wl0pc1s2xh; path=/; HttpOnly","CaptchaKey":"22887","CaptchaPath":"http://procesos.ramajudicial.gov.co/consultaprocesos/Captcha/CaptchaHandler.ashx?key=22887","ProcessNumber":null,"CaptchaResult":0,"ResultData":null},{"Cookie":"ASP.NET_SessionId=news1ej2vd5jdjjwcrwpmhnc; path=/; HttpOnly","CaptchaKey":"48165","CaptchaPath":"http://procesos.ramajudicial.gov.co/consultaprocesos/Captcha/CaptchaHandler.ashx?key=48165","ProcessNumber":null,"CaptchaResult":0,"ResultData":null},{"Cookie":"ASP.NET_SessionId=rpdbwdht2z4ynjjqnmzbt4ss; path=/; HttpOnly","CaptchaKey":"15355","CaptchaPath":"http://procesos.ramajudicial.gov.co/consultaprocesos/Captcha/CaptchaHandler.ashx?key=15355","ProcessNumber":null,"CaptchaResult":0,"ResultData":null},{"Cookie":"ASP.NET_SessionId=th0sryvcsnnz20tvx40up3f3; path=/; HttpOnly","CaptchaKey":"83418","CaptchaPath":"http://procesos.ramajudicial.gov.co/consultaprocesos/Captcha/CaptchaHandler.ashx?key=83418","ProcessNumber":null,"CaptchaResult":0,"ResultData":null},{"Cookie":"ASP.NET_SessionId=xn4ralskcojywss23badd4af; path=/; HttpOnly","CaptchaKey":"52683","CaptchaPath":"http://procesos.ramajudicial.gov.co/consultaprocesos/Captcha/CaptchaHandler.ashx?key=52683","ProcessNumber":null,"CaptchaResult":0,"ResultData":null},{"Cookie":"ASP.NET_SessionId=1yl1kbciyau5o0eoxlfn2pc0; path=/; HttpOnly","CaptchaKey":"32534","CaptchaPath":"http://procesos.ramajudicial.gov.co/consultaprocesos/Captcha/CaptchaHandler.ashx?key=32534","ProcessNumber":null,"CaptchaResult":0,"ResultData":null},{"Cookie":"ASP.NET_SessionId=kaozflxbhjji2ejrtjeyrd5g; path=/; HttpOnly","CaptchaKey":"51198","CaptchaPath":"http://procesos.ramajudicial.gov.co/consultaprocesos/Captcha/CaptchaHandler.ashx?key=51198","ProcessNumber":null,"CaptchaResult":0,"ResultData":null},{"Cookie":"ASP.NET_SessionId=qpcpexrqfwqj0sx1pza4mily; path=/; HttpOnly","CaptchaKey":"95184","CaptchaPath":"http://procesos.ramajudicial.gov.co/consultaprocesos/Captcha/CaptchaHandler.ashx?key=95184","ProcessNumber":null,"CaptchaResult":0,"ResultData":null},{"Cookie":"ASP.NET_SessionId=ypqgaomnccu2xbxggiiu3hmp; path=/; HttpOnly","CaptchaKey":"24698","CaptchaPath":"http://procesos.ramajudicial.gov.co/consultaprocesos/Captcha/CaptchaHandler.ashx?key=24698","ProcessNumber":null,"CaptchaResult":0,"ResultData":null},{"Cookie":"ASP.NET_SessionId=zf2ay41qddvmgrcba3xdgiqc; path=/; HttpOnly","CaptchaKey":"96385","CaptchaPath":"http://procesos.ramajudicial.gov.co/consultaprocesos/Captcha/CaptchaHandler.ashx?key=96385","ProcessNumber":null,"CaptchaResult":0,"ResultData":null},{"Cookie":"ASP.NET_SessionId=gmrswvunnwzdyqhkjdnu220r; path=/; HttpOnly","CaptchaKey":"91233","CaptchaPath":"http://procesos.ramajudicial.gov.co/consultaprocesos/Captcha/CaptchaHandler.ashx?key=91233","ProcessNumber":null,"CaptchaResult":0,"ResultData":null},{"Cookie":"ASP.NET_SessionId=ihe1ig4fok2yzlvlodbc0ng1; path=/; HttpOnly","CaptchaKey":"11730","CaptchaPath":"http://procesos.ramajudicial.gov.co/consultaprocesos/Captcha/CaptchaHandler.ashx?key=11730","ProcessNumber":null,"CaptchaResult":0,"ResultData":null},{"Cookie":"ASP.NET_SessionId=fyvtpaixp2qcberovdxkef5y; path=/; HttpOnly","CaptchaKey":"99092","CaptchaPath":"http://procesos.ramajudicial.gov.co/consultaprocesos/Captcha/CaptchaHandler.ashx?key=99092","ProcessNumber":null,"CaptchaResult":0,"ResultData":null},{"Cookie":"ASP.NET_SessionId=slmgceepgev0d5pnen2awmfq; path=/; HttpOnly","CaptchaKey":"10530","CaptchaPath":"http://procesos.ramajudicial.gov.co/consultaprocesos/Captcha/CaptchaHandler.ashx?key=10530","ProcessNumber":null,"CaptchaResult":0,"ResultData":null},{"Cookie":"ASP.NET_SessionId=h1ulqhtpaxfnjv4imeqqwqyw; path=/; HttpOnly","CaptchaKey":"47879","CaptchaPath":"http://procesos.ramajudicial.gov.co/consultaprocesos/Captcha/CaptchaHandler.ashx?key=47879","ProcessNumber":null,"CaptchaResult":0,"ResultData":null},{"Cookie":"ASP.NET_SessionId=ktls4zx2dsgieydawciw2pxm; path=/; HttpOnly","CaptchaKey":"25002","CaptchaPath":"http://procesos.ramajudicial.gov.co/consultaprocesos/Captcha/CaptchaHandler.ashx?key=25002","ProcessNumber":null,"CaptchaResult":0,"ResultData":null},{"Cookie":"ASP.NET_SessionId=avqcydnyhhre32gzf1oqvtwf; path=/; HttpOnly","CaptchaKey":"69271","CaptchaPath":"http://procesos.ramajudicial.gov.co/consultaprocesos/Captcha/CaptchaHandler.ashx?key=69271","ProcessNumber":null,"CaptchaResult":0,"ResultData":null},{"Cookie":"ASP.NET_SessionId=iz4bnesnyry2vfijp2gqno1s; path=/; HttpOnly","CaptchaKey":"95772","CaptchaPath":"http://procesos.ramajudicial.gov.co/consultaprocesos/Captcha/CaptchaHandler.ashx?key=95772","ProcessNumber":null,"CaptchaResult":0,"ResultData":null},{"Cookie":"ASP.NET_SessionId=1yv53o4bopfw5zkd3qzhgatr; path=/; HttpOnly","CaptchaKey":"94266","CaptchaPath":"http://procesos.ramajudicial.gov.co/consultaprocesos/Captcha/CaptchaHandler.ashx?key=94266","ProcessNumber":null,"CaptchaResult":0,"ResultData":null},{"Cookie":"ASP.NET_SessionId=xtevhwcph3kl5nrkmixcsamu; path=/; HttpOnly","CaptchaKey":"30133","CaptchaPath":"http://procesos.ramajudicial.gov.co/consultaprocesos/Captcha/CaptchaHandler.ashx?key=30133","ProcessNumber":null,"CaptchaResult":0,"ResultData":null},{"Cookie":"ASP.NET_SessionId=by2s1fdhz5tedofp0h0z5f0m; path=/; HttpOnly","CaptchaKey":"60541","CaptchaPath":"http://procesos.ramajudicial.gov.co/consultaprocesos/Captcha/CaptchaHandler.ashx?key=60541","ProcessNumber":null,"CaptchaResult":0,"ResultData":null},{"Cookie":"ASP.NET_SessionId=ligxsuzvh4qvjtgq4ot0h23u; path=/; HttpOnly","CaptchaKey":"79510","CaptchaPath":"http://procesos.ramajudicial.gov.co/consultaprocesos/Captcha/CaptchaHandler.ashx?key=79510","ProcessNumber":null,"CaptchaResult":0,"ResultData":null},{"Cookie":"ASP.NET_SessionId=pjprwh1xv5ya0gqa3pvjtbbs; path=/; HttpOnly","CaptchaKey":"39759","CaptchaPath":"http://procesos.ramajudicial.gov.co/consultaprocesos/Captcha/CaptchaHandler.ashx?key=39759","ProcessNumber":null,"CaptchaResult":0,"ResultData":null},{"Cookie":"ASP.NET_SessionId=ni0gcgozh0hfrae3m44u4kkn; path=/; HttpOnly","CaptchaKey":"17165","CaptchaPath":"http://procesos.ramajudicial.gov.co/consultaprocesos/Captcha/CaptchaHandler.ashx?key=17165","ProcessNumber":null,"CaptchaResult":0,"ResultData":null},{"Cookie":"ASP.NET_SessionId=wu3uyc5xzkejyuyhlgpcqtlj; path=/; HttpOnly","CaptchaKey":"31922","CaptchaPath":"http://procesos.ramajudicial.gov.co/consultaprocesos/Captcha/CaptchaHandler.ashx?key=31922","ProcessNumber":null,"CaptchaResult":0,"ResultData":null},{"Cookie":"ASP.NET_SessionId=xviku3opegle2xtwtl4yy1dy; path=/; HttpOnly","CaptchaKey":"18083","CaptchaPath":"http://procesos.ramajudicial.gov.co/consultaprocesos/Captcha/CaptchaHandler.ashx?key=18083","ProcessNumber":null,"CaptchaResult":0,"ResultData":null},{"Cookie":"ASP.NET_SessionId=p2u5leacdihawmb3gtbq100c; path=/; HttpOnly","CaptchaKey":"9941","CaptchaPath":"http://procesos.ramajudicial.gov.co/consultaprocesos/Captcha/CaptchaHandler.ashx?key=9941","ProcessNumber":null,"CaptchaResult":0,"ResultData":null},{"Cookie":"ASP.NET_SessionId=xw12dxrslnwyyhuk1nnzfdyu; path=/; HttpOnly","CaptchaKey":"33123","CaptchaPath":"http://procesos.ramajudicial.gov.co/consultaprocesos/Captcha/CaptchaHandler.ashx?key=33123","ProcessNumber":null,"CaptchaResult":0,"ResultData":null},{"Cookie":"ASP.NET_SessionId=p2navm04rjov5jvaqktovvoh; path=/; HttpOnly","CaptchaKey":"2409","CaptchaPath":"http://procesos.ramajudicial.gov.co/consultaprocesos/Captcha/CaptchaHandler.ashx?key=2409","ProcessNumber":null,"CaptchaResult":0,"ResultData":null},{"Cookie":"ASP.NET_SessionId=ypvtaclkqulupposycfampqz; path=/; HttpOnly","CaptchaKey":"54515","CaptchaPath":"http://procesos.ramajudicial.gov.co/consultaprocesos/Captcha/CaptchaHandler.ashx?key=54515","ProcessNumber":null,"CaptchaResult":0,"ResultData":null},{"Cookie":"ASP.NET_SessionId=l5t5ljr5srgjbgl0o5tgyxb1; path=/; HttpOnly","CaptchaKey":"44276","CaptchaPath":"http://procesos.ramajudicial.gov.co/consultaprocesos/Captcha/CaptchaHandler.ashx?key=44276","ProcessNumber":null,"CaptchaResult":0,"ResultData":null},{"Cookie":"ASP.NET_SessionId=nc0s3r0confu1kbpkxsfaczo; path=/; HttpOnly","CaptchaKey":"32839","CaptchaPath":"http://procesos.ramajudicial.gov.co/consultaprocesos/Captcha/CaptchaHandler.ashx?key=32839","ProcessNumber":null,"CaptchaResult":0,"ResultData":null},{"Cookie":"ASP.NET_SessionId=eww2bgfvsklm0w1cdlczrjkj; path=/; HttpOnly","CaptchaKey":"44889","CaptchaPath":"http://procesos.ramajudicial.gov.co/consultaprocesos/Captcha/CaptchaHandler.ashx?key=44889","ProcessNumber":null,"CaptchaResult":0,"ResultData":null},{"Cookie":"ASP.NET_SessionId=p55kv3mwscga2xqx3fz4zgbq; path=/; HttpOnly","CaptchaKey":"81037","CaptchaPath":"http://procesos.ramajudicial.gov.co/consultaprocesos/Captcha/CaptchaHandler.ashx?key=81037","ProcessNumber":null,"CaptchaResult":0,"ResultData":null},{"Cookie":"ASP.NET_SessionId=23hr03v2j33tkoa3lstvbzol; path=/; HttpOnly","CaptchaKey":"10551","CaptchaPath":"http://procesos.ramajudicial.gov.co/consultaprocesos/Captcha/CaptchaHandler.ashx?key=10551","ProcessNumber":null,"CaptchaResult":0,"ResultData":null},{"Cookie":"ASP.NET_SessionId=v5buki0p4gxtphwirn4yvrou; path=/; HttpOnly","CaptchaKey":"10246","CaptchaPath":"http://procesos.ramajudicial.gov.co/consultaprocesos/Captcha/CaptchaHandler.ashx?key=10246","ProcessNumber":null,"CaptchaResult":0,"ResultData":null},{"Cookie":"ASP.NET_SessionId=xkpbvibajpawyjtp0vidmym3; path=/; HttpOnly","CaptchaKey":"93675","CaptchaPath":"http://procesos.ramajudicial.gov.co/consultaprocesos/Captcha/CaptchaHandler.ashx?key=93675","ProcessNumber":null,"CaptchaResult":0,"ResultData":null},{"Cookie":"ASP.NET_SessionId=kv3uag3rluilyqp3bvqd2li4; path=/; HttpOnly","CaptchaKey":"13563","CaptchaPath":"http://procesos.ramajudicial.gov.co/consultaprocesos/Captcha/CaptchaHandler.ashx?key=13563","ProcessNumber":null,"CaptchaResult":0,"ResultData":null},{"Cookie":"ASP.NET_SessionId=ffncu2kan2ibcsn1gk554j3c; path=/; HttpOnly","CaptchaKey":"18388","CaptchaPath":"http://procesos.ramajudicial.gov.co/consultaprocesos/Captcha/CaptchaHandler.ashx?key=18388","ProcessNumber":null,"CaptchaResult":0,"ResultData":null},{"Cookie":"ASP.NET_SessionId=qjdaeoqprfrcxzzwg1dq2vr0; path=/; HttpOnly","CaptchaKey":"61456","CaptchaPath":"http://procesos.ramajudicial.gov.co/consultaprocesos/Captcha/CaptchaHandler.ashx?key=61456","ProcessNumber":null,"CaptchaResult":0,"ResultData":null},{"Cookie":"ASP.NET_SessionId=kkwj2fawnxoylsh22d401imv; path=/; HttpOnly","CaptchaKey":"76212","CaptchaPath":"http://procesos.ramajudicial.gov.co/consultaprocesos/Captcha/CaptchaHandler.ashx?key=76212","ProcessNumber":null,"CaptchaResult":0,"ResultData":null},{"Cookie":"ASP.NET_SessionId=p1jjscudjqkrahss0hc4y0zg; path=/; HttpOnly","CaptchaKey":"49406","CaptchaPath":"http://procesos.ramajudicial.gov.co/consultaprocesos/Captcha/CaptchaHandler.ashx?key=49406","ProcessNumber":null,"CaptchaResult":0,"ResultData":null},{"Cookie":"ASP.NET_SessionId=kcmqwwzjrsxszmlvey2izgna; path=/; HttpOnly","CaptchaKey":"66281","CaptchaPath":"http://procesos.ramajudicial.gov.co/consultaprocesos/Captcha/CaptchaHandler.ashx?key=66281","ProcessNumber":null,"CaptchaResult":0,"ResultData":null},{"Cookie":"ASP.NET_SessionId=l2o3qpeqxz1kecx3mvktm4gp; path=/; HttpOnly","CaptchaKey":"45477","CaptchaPath":"http://procesos.ramajudicial.gov.co/consultaprocesos/Captcha/CaptchaHandler.ashx?key=45477","ProcessNumber":null,"CaptchaResult":0,"ResultData":null},{"Cookie":"ASP.NET_SessionId=lihpera5dcllfa0jzlcozrdn; path=/; HttpOnly","CaptchaKey":"81342","CaptchaPath":"http://procesos.ramajudicial.gov.co/consultaprocesos/Captcha/CaptchaHandler.ashx?key=81342","ProcessNumber":null,"CaptchaResult":0,"ResultData":null},{"Cookie":"ASP.NET_SessionId=w1evz1edraq45l0dqlf1h5zm; path=/; HttpOnly","CaptchaKey":"18366","CaptchaPath":"http://procesos.ramajudicial.gov.co/consultaprocesos/Captcha/CaptchaHandler.ashx?key=18366","ProcessNumber":null,"CaptchaResult":0,"ResultData":null},{"Cookie":"ASP.NET_SessionId=iryrjspqj4ikackbrpbdokan; path=/; HttpOnly","CaptchaKey":"46700","CaptchaPath":"http://procesos.ramajudicial.gov.co/consultaprocesos/Captcha/CaptchaHandler.ashx?key=46700","ProcessNumber":null,"CaptchaResult":0,"ResultData":null},{"Cookie":"ASP.NET_SessionId=eiyqhzk2x0wlklj2pqcs0bqn; path=/; HttpOnly","CaptchaKey":"78919","CaptchaPath":"http://procesos.ramajudicial.gov.co/consultaprocesos/Captcha/CaptchaHandler.ashx?key=78919","ProcessNumber":null,"CaptchaResult":0,"ResultData":null},{"Cookie":"ASP.NET_SessionId=yfywutc0t35zbhfworveloym; path=/; HttpOnly","CaptchaKey":"66586","CaptchaPath":"http://procesos.ramajudicial.gov.co/consultaprocesos/Captcha/CaptchaHandler.ashx?key=66586","ProcessNumber":null,"CaptchaResult":0,"ResultData":null},{"Cookie":"ASP.NET_SessionId=5smeiehocpcdakwseixuhwhd; path=/; HttpOnly","CaptchaKey":"36156","CaptchaPath":"http://procesos.ramajudicial.gov.co/consultaprocesos/Captcha/CaptchaHandler.ashx?key=36156","ProcessNumber":null,"CaptchaResult":0,"ResultData":null},{"Cookie":"ASP.NET_SessionId=ad2qroxn1ein1pwab5yinhs5; path=/; HttpOnly","CaptchaKey":"84049","CaptchaPath":"http://procesos.ramajudicial.gov.co/consultaprocesos/Captcha/CaptchaHandler.ashx?key=84049","ProcessNumber":null,"CaptchaResult":0,"ResultData":null},{"Cookie":"ASP.NET_SessionId=3rvjdtiiygoiq4igm1ag0xbj; path=/; HttpOnly","CaptchaKey":"64163","CaptchaPath":"http://procesos.ramajudicial.gov.co/consultaprocesos/Captcha/CaptchaHandler.ashx?key=64163","ProcessNumber":null,"CaptchaResult":0,"ResultData":null},{"Cookie":"ASP.NET_SessionId=lnhwksanog550dpefrjcflnt; path=/; HttpOnly","CaptchaKey":"98805","CaptchaPath":"http://procesos.ramajudicial.gov.co/consultaprocesos/Captcha/CaptchaHandler.ashx?key=98805","ProcessNumber":null,"CaptchaResult":0,"ResultData":null},{"Cookie":"ASP.NET_SessionId=lzhdo5qtlyclzndda55qtki0; path=/; HttpOnly","CaptchaKey":"59014","CaptchaPath":"http://procesos.ramajudicial.gov.co/consultaprocesos/Captcha/CaptchaHandler.ashx?key=59014","ProcessNumber":null,"CaptchaResult":0,"ResultData":null}]